{
  "annotations": {
    "list": [
      {
        "builtIn": 1,
        "datasource": "-- Grafana --",
        "enable": true,
        "hide": true,
        "iconColor": "rgba(0, 211, 255, 1)",
        "name": "Annotations & Alerts",
        "type": "dashboard"
      }
    ]
  },
  "editable": true,
  "gnetId": null,
  "graphTooltip": 0,
  "hideControls": false,
  "id": null,
  "links": [],
  "refresh": "1m",
  "rows": [
    {
      "collapse": false,
      "height": "300",
      "panels": [
        {
          "aliasColors": {},
          "bars": false,
          "dashLength": 10,
          "dashes": false,
          "datasource": null,
          "description": "The I/O throughput on this OST.",
          "fill": 1,
          "id": 75,
          "legend": {
            "avg": false,
            "current": false,
            "max": false,
            "min": false,
            "show": true,
            "total": false,
            "values": false
          },
          "lines": true,
          "linewidth": 1,
          "links": [],
          "nullPointMode": "null",
          "percentage": false,
          "pointradius": 5,
          "points": false,
          "renderer": "flot",
          "seriesOverrides": [],
          "spaceLength": 10,
          "span": 4,
          "stack": false,
          "steppedLine": false,
          "targets": [
            {
              "alias": "I/O Throughput",
              "dsType": "influxdb",
              "groupBy": [],
              "measurement": "cqm_ost_stats_bytes-fqdn-fs_name",
              "orderByTime": "ASC",
              "policy": "default",
              "query": "SELECT \"sum\" FROM \"cqm_ost_stats_bytes-fs_name-ost_index\" WHERE \"fs_name\" = '$fs_name' AND \"optype\" = 'write' AND $timeFilter GROUP BY \"ost_index\"",
              "rawQuery": false,
              "refId": "A",
              "resultFormat": "time_series",
              "select": [
                [
                  {
                    "params": [
                      "sum"
                    ],
                    "type": "field"
                  }
                ]
              ],
              "tags": [
                {
                  "key": "fs_name",
                  "operator": "=",
                  "value": "$fs_name"
                },
                {
                  "condition": "AND",
                  "key": "fqdn",
                  "operator": "=",
                  "value": "$oss"
                }
              ]
            }
          ],
          "thresholds": [],
          "timeFrom": null,
          "timeShift": null,
          "title": "I/O Throughput",
          "tooltip": {
            "shared": true,
            "sort": 0,
            "value_type": "individual"
          },
          "type": "graph",
          "xaxis": {
            "buckets": null,
            "mode": "time",
            "name": null,
            "show": true,
            "values": []
          },
          "yaxes": [
            {
              "format": "Bps",
              "label": null,
              "logBase": 1,
              "max": null,
              "min": "0",
              "show": true
            },
            {
              "format": "short",
              "label": null,
              "logBase": 1,
              "max": null,
              "min": null,
              "show": false
            }
          ]
        },
        {
          "aliasColors": {},
          "bars": false,
          "dashLength": 10,
          "dashes": false,
          "datasource": null,
          "description": "The write throughput on this OST.",
          "fill": 1,
          "id": 84,
          "legend": {
            "avg": false,
            "current": false,
            "max": false,
            "min": false,
            "show": true,
            "total": false,
            "values": false
          },
          "lines": true,
          "linewidth": 1,
          "links": [],
          "nullPointMode": "null",
          "percentage": false,
          "pointradius": 5,
          "points": false,
          "renderer": "flot",
          "seriesOverrides": [],
          "spaceLength": 10,
          "span": 4,
          "stack": false,
          "steppedLine": false,
          "targets": [
            {
              "alias": "Write Throughput",
              "dsType": "influxdb",
              "groupBy": [],
              "measurement": "cqm_ost_stats_bytes-fqdn-fs_name-optype",
              "orderByTime": "ASC",
              "policy": "default",
              "query": "SELECT \"sum\" FROM \"cqm_ost_stats_bytes-fs_name-optype-ost_index\" WHERE \"fs_name\" = '$fs_name' AND \"optype\" = 'write' AND $timeFilter GROUP BY \"ost_index\"",
              "rawQuery": false,
              "refId": "A",
              "resultFormat": "time_series",
              "select": [
                [
                  {
                    "params": [
                      "sum"
                    ],
                    "type": "field"
                  }
                ]
              ],
              "tags": [
                {
                  "key": "fs_name",
                  "operator": "=",
                  "value": "$fs_name"
                },
                {
                  "condition": "AND",
                  "key": "optype",
                  "operator": "=",
                  "value": "write"
                },
                {
                  "condition": "AND",
                  "key": "fqdn",
                  "operator": "=",
                  "value": "$oss"
                }
              ]
            }
          ],
          "thresholds": [],
          "timeFrom": null,
          "timeShift": null,
          "title": "Write Throughput",
          "tooltip": {
            "shared": true,
            "sort": 0,
            "value_type": "individual"
          },
          "type": "graph",
          "xaxis": {
            "buckets": null,
            "mode": "time",
            "name": null,
            "show": true,
            "values": []
          },
          "yaxes": [
            {
              "format": "Bps",
              "label": null,
              "logBase": 1,
              "max": null,
              "min": "0",
              "show": true
            },
            {
              "format": "short",
              "label": null,
              "logBase": 1,
              "max": null,
              "min": null,
              "show": false
            }
          ]
        },
        {
          "aliasColors": {},
          "bars": false,
          "dashLength": 10,
          "dashes": false,
          "datasource": null,
          "description": "The read throughput on this OST.",
          "fill": 1,
          "id": 85,
          "legend": {
            "avg": false,
            "current": false,
            "max": false,
            "min": false,
            "show": true,
            "total": false,
            "values": false
          },
          "lines": true,
          "linewidth": 1,
          "links": [],
          "nullPointMode": "null",
          "percentage": false,
          "pointradius": 5,
          "points": false,
          "renderer": "flot",
          "seriesOverrides": [],
          "spaceLength": 10,
          "span": 4,
          "stack": false,
          "steppedLine": false,
          "targets": [
            {
              "alias": "Read Throughput",
              "dsType": "influxdb",
              "groupBy": [],
              "measurement": "cqm_ost_stats_bytes-fqdn-fs_name-optype",
              "orderByTime": "ASC",
              "policy": "default",
              "query": "SELECT \"sum\" FROM \"cqm_ost_stats_bytes-fs_name-optype-ost_index\" WHERE \"fs_name\" = '$fs_name' AND \"optype\" = 'write' AND $timeFilter GROUP BY \"ost_index\"",
              "rawQuery": false,
              "refId": "A",
              "resultFormat": "time_series",
              "select": [
                [
                  {
                    "params": [
                      "sum"
                    ],
                    "type": "field"
                  }
                ]
              ],
              "tags": [
                {
                  "key": "fs_name",
                  "operator": "=",
                  "value": "$fs_name"
                },
                {
                  "condition": "AND",
                  "key": "optype",
                  "operator": "=",
                  "value": "read"
                },
                {
                  "condition": "AND",
                  "key": "fqdn",
                  "operator": "=",
                  "value": "$oss"
                }
              ]
            }
          ],
          "thresholds": [],
          "timeFrom": null,
          "timeShift": null,
          "title": "Read Throughput",
          "tooltip": {
            "shared": true,
            "sort": 0,
            "value_type": "individual"
          },
          "type": "graph",
          "xaxis": {
            "buckets": null,
            "mode": "time",
            "name": null,
            "show": true,
            "values": []
          },
          "yaxes": [
            {
              "format": "Bps",
              "label": null,
              "logBase": 1,
              "max": null,
              "min": "0",
              "show": true
            },
            {
              "format": "short",
              "label": null,
              "logBase": 1,
              "max": null,
              "min": null,
              "show": false
            }
          ]
        }
      ],
      "repeat": null,
      "repeatIteration": null,
      "repeatRowId": null,
      "showTitle": false,
      "title": "I/O Bandwith",
      "titleSize": "h6"
    }
  ],
  "schemaVersion": 14,
  "style": "dark",
  "tags": [],
  "templating": {
    "list": [
      {
        "allValue": null,
        "current": {
          "text": "es2",
          "value": "es2"
        },
        "datasource": "esmon_datasource",
        "hide": 0,
        "includeAll": false,
        "label": "Filesystem Name",
        "multi": false,
        "name": "fs_name",
        "options": [],
        "query": "SHOW TAG VALUES FROM \"ost_kbytesinfo_used\" WITH KEY = fs_name",
        "refresh": 1,
        "regex": "",
        "sort": 3,
        "tagValuesQuery": "",
        "tags": [],
        "tagsQuery": "",
        "type": "query",
        "useTags": false
      },
      {
        "allValue": null,
        "current": {
          "text": "server17_esmom_vm4",
          "value": "server17_esmom_vm4"
        },
        "datasource": "esmon_datasource",
        "hide": 0,
        "includeAll": false,
        "label": "OSS",
        "multi": false,
        "name": "oss",
        "options": [],
        "query": "SHOW TAG VALUES FROM \"ost_kbytesinfo_used\" WITH KEY = fqdn WHERE \"fs_name\" = '$fs_name'",
        "refresh": 1,
        "regex": "",
        "sort": 1,
        "tagValuesQuery": "",
        "tags": [],
        "tagsQuery": "",
        "type": "query",
        "useTags": false
      }
    ]
  },
  "time": {
    "from": "now-1h",
    "to": "now"
  },
  "timepicker": {
    "refresh_intervals": [
      "1m"
    ],
    "time_options": [
      "5m",
      "15m",
      "1h",
      "6h",
      "12h",
      "24h",
      "2d",
      "7d",
      "30d"
    ]
  },
  "timezone": "browser",
  "title": "Lustre OSS",
  "version": 1
}

